metastore/VERSION
metastore/__init__.py
metastore/artifacts.py
metastore/database.py
metastore/handlers.py
metastore/project.py
metastore/storage.py
metastore/utils.py
infuseai_metastore-0.0.3.dist-info/METADATA
infuseai_metastore-0.0.3.dist-info/WHEEL
infuseai_metastore-0.0.3.dist-info/top_level.txt
infuseai_metastore-0.0.3.dist-info/RECORD
