Metadata-Version: 2.1
Name: infuseai-metastore
Version: 0.0.3
Summary: MetaStore
Home-page: https://github.com/InfuseAI/mm-only-details/issues
Author: qrtt1
Author-email: qrtt1@infuseai.io
License: UNKNOWN
Project-URL: Bug Tracker, https://github.com/InfuseAI/primehub/issues
Platform: UNKNOWN
Classifier: Programming Language :: Python :: 3
Classifier: License :: OSI Approved :: Apache Software License
Classifier: Operating System :: OS Independent
Classifier: Development Status :: 4 - Beta
Requires-Python: >=3.6
Requires-Dist: kafka-python
Requires-Dist: boto3
Requires-Dist: requests
Requires-Dist: pandas
Provides-Extra: dev
Requires-Dist: twine ; extra == 'dev'
